{"card_name": "Weequay Beastmaster", "color": "R", "rarity": "uncommon", "type": "Creature \u2013 Weequay Shaman", "number": 132, "color_identity": "R", "cost": "{1}{R}", "rules_text": "Monstrosity abilities you activate cost {1} less to activate.\nWhenever a creature you control becomes monstrous, put a +1/+1 counter on that creature.", "flavor_text": "[i][/i]", "pt": "2/1", "special_text": "", "shape": "normal", "set": "SWTG", "loyalty": "", "artist": "Jacob Atienza", "notes": "", "image_type": "png"}