{"card_name": "Senator Padm\u00e9 Amidala", "color": "WU", "rarity": "uncommon", "type": "Legendary Creature \u2013 Human Advisor", "number": 219, "color_identity": "WU", "cost": "{W}{U}", "rules_text": "Lifelink\nAt the beginning of your upkeep, you may return another creature you control to its owner's hand.", "flavor_text": "[i][/i]", "pt": "2/2", "special_text": "", "shape": "normal", "set": "SWTG", "loyalty": "", "artist": "Jerry Vanderstelt", "notes": "Azorius\nrework", "image_type": "png"}