{"card_name": "Lockdown", "color": "W", "rarity": "common", "type": "Enchantment \u2013 Aura", "number": 21, "color_identity": "W", "cost": "{2}{W}", "rules_text": "Enchant artifact or creature\nEnchanted permanent can't attack or block and its activated abilities can't be activated.", "flavor_text": "[i]\u201cYou are a part of the Rebel Alliance and a traitor. Take her away!\u201d\n\u2014Darth Vader[/i]", "pt": "", "special_text": "", "shape": "normal", "set": "SWTG", "loyalty": "", "artist": "The Journal of Master Gnost-Dural", "notes": "", "image_type": "png"}