{"card_name": "Trade Federation Battleship", "color": "WUB", "rarity": "rare", "type": "Kindred Artifact \u2013 Droid Vehicle", "number": 226, "color_identity": "WUB", "cost": "{3}{W}{U}{B}", "rules_text": "Spaceflight [i](This creature can only block or be blocked by creatures with spaceflight.)[/i]\nOther Droid creatures you control get +1/+1\n{3}, {T}: Create two 1/1 colorless Droid artifact creature tokens.\nCrew 3", "flavor_text": "[i][/i]", "pt": "0/6", "special_text": "", "shape": "normal", "set": "SWTG", "loyalty": "", "artist": "The Phantom Menace", "notes": "!token Droid SWTG<2>;\nEsper", "image_type": "png"}