{"card_name": "Gleaming Seraph", "color": "W", "rarity": "uncommon", "type": "Creature \u2013 Angel", "number": 20, "color_identity": "W", "cost": "{3}{W}{W}{W}", "rules_text": "Flying\n[i]Morbid[/i] \u2013 When this creature enters, if a creature died this turn, return each creature card in your graveyard that was put there from the battlefield this turn to the battlefield.", "flavor_text": "[i][/i]", "pt": "4/4", "special_text": "", "shape": "normal", "set": "ANX", "loyalty": "", "artist": "Jun Tacuyan", "notes": "", "image_type": "png"}