{"card_name": "Tovalar the Hunter", "color": "RG", "rarity": "mythic", "type": "Legendary Creature \u2013 Human Werewolf", "number": 222, "color_identity": "RG", "cost": "{1}{R}{G}", "rules_text": "First strike\nWhenever Tovalar deals combat damage to a player, transform him.\nAt the beginning of each upkeep, if no spells were cast last turn, transform Tovalar.", "flavor_text": "[i][/i]", "pt": "3/1", "special_text": "", "shape": "transform double faced", "set": "ANX", "loyalty": "", "artist": "G\u00f6kberk Kaya", "card_name2": "Tovalar Howlpack Leader", "color2": "RG", "type2": "Legendary Creature \u2013 Werewolf", "cost2": "", "rules_text2": "Double strike\nAt the beginning of each upkeep, if a player cast two or more spells last turn, transform Tovalar.", "flavor_text2": "[i][/i]", "pt2": "3/1", "special_text2": "", "loyalty2": "", "artist2": "sandara on deviantart", "notes": "!exportname Tovalar the Hunter\n!backfacename Tovalar Howlpack Leader", "image_type": "png"}