{"card_name": "The Eviscerator", "color": "BR", "rarity": "uncommon", "type": "Legendary Artifact \u2013 Vehicle", "number": 211, "color_identity": "BR", "cost": "{1}{B}{R}", "rules_text": "Trample, haste\nThe Eviscerator can't block.\nWhenever The Eviscerator attacks, sacrifice each creature that crewed it this turn at the end of combat.\nCrew 1", "flavor_text": "[i][/i]", "pt": "5/5", "special_text": "", "shape": "normal", "set": "VRN", "loyalty": "", "artist": "Bigball Gao", "notes": "Rakdos U", "image_type": "png"}