{"card_name": "Forsaken Legionnaire", "color": "W", "rarity": "common", "type": "Artifact Creature \u2013 Phyrexian Soldier", "number": 22, "color_identity": "W", "cost": "{1}{W}", "rules_text": "This creature has first strike as long as you control two or more attacking artifact creatures.", "flavor_text": "[i]When Realmbreaker broke through eternity, the armies of Phyrexia made light of Vryn's civil affairs.[/i]", "pt": "3/1", "special_text": "", "shape": "normal", "set": "VRN", "loyalty": "", "artist": "Deiv Calviz", "notes": "", "image_type": "png"}