{"card_name": "Sheoldred, Blighted Thane", "color": "B", "rarity": "mythic", "type": "Legendary Creature \u2013 Phyrexian Praetor", "number": 103, "color_identity": "B", "cost": "{4}{B}{B}", "rules_text": "Menace\nWhenever a creature you control attacks, the defending player loses 1 life.\nAt the beginning of your end step, each opponent who lost no life this turn sacrifices a creature.", "flavor_text": "[i][/i]", "pt": "4/5", "special_text": "", "shape": "normal", "set": "EZA", "loyalty": "", "artist": "homoseptimus on deviantart", "notes": "", "image_type": "png"}