{"card_name": "Ei'tal Crawler", "color": "G", "rarity": "uncommon", "type": "Creature \u2013 Phyrexian Beast Horror", "number": 158, "color_identity": "G", "cost": "{3}{G}{G}", "rules_text": "Wither [i](This deals damage to creatures in the form of -1/-1 counters.)[/i]\nWhenever a creature you don't control dies, put a -1/-1 counter on this creature.\n{1}{G}{G}, Remove three -1/-1 counters from this creature: Put three +1/+1 counters on target creature you control.", "flavor_text": "[i][/i]", "pt": "3/6", "special_text": "", "shape": "normal", "set": "EZA", "loyalty": "", "artist": "Vincent Van Hoof", "notes": "", "image_type": "png"}