{"card_name": "Ja'Madt, Warleader", "color": "WR", "rarity": "mythic", "type": "Legendary Creature \u2013 Human Knight", "number": 205, "color_identity": "WR", "cost": "{2}{R}{W}", "rules_text": "Vigilance\nWhenever Ja'Madt attacks, he deals X damage to any non-player target, where X is the greatest power among attacking creatures.\nTap three untapped creatures you control: Ja'Madt gains indestructible until end of turn.", "flavor_text": "[i][/i]", "pt": "3/3", "special_text": "", "shape": "normal", "set": "EZA", "loyalty": "", "artist": "Rob Joseph", "notes": "", "image_type": "png"}