{"card_name": "Curse of Conflagration", "color": "R", "rarity": "uncommon", "type": "Enchantment \u2013 Aura Curse", "number": 134, "color_identity": "R", "cost": "{5}{R}", "rules_text": "Enchant player\nWhenever enchanted player casts a spell, this Curse deals X damage to them or up to one target creature or planeswalker they control, where X is the number of Curses attached to enchanted player.", "flavor_text": "[i][/i]", "pt": "", "special_text": "", "shape": "normal", "set": "AZG", "loyalty": "", "artist": "Feig-Art on deviantart", "notes": "", "image_type": "png"}