{"card_name": "Bitterheart Witch", "color": "B", "rarity": "uncommon", "type": "Creature \u2013 Human Shaman", "number": 94, "color_identity": "B", "cost": "{4}{B}", "rules_text": "Deathtouch\nWhen this creature dies, you may search your library for a Curse card, put it onto the battlefield attached to target player, then shuffle.", "flavor_text": "[i][/i]", "pt": "1/2", "special_text": "", "shape": "normal", "set": "AZG", "loyalty": "", "artist": "Karl Kopinski", "notes": "", "image_type": "png"}